MANIFEST.in
README.md
setup.py
baconql/VERSION
baconql/__init__.py
baconql/cli.py
baconql.egg-info/PKG-INFO
baconql.egg-info/SOURCES.txt
baconql.egg-info/dependency_links.txt
baconql.egg-info/entry_points.txt
baconql.egg-info/requires.txt
baconql.egg-info/top_level.txt
baconql/compiler/F.py
baconql/compiler/__init__.py
baconql/compiler/defs.py
baconql/compiler/exceptions.py
baconql/compiler/loader.py
baconql/compiler/parser.py
baconql/compiler/python.py
baconql/compiler/render.py
baconql/compiler/templates/__init__.py
baconql/compiler/templates/_result_affected.py
baconql/compiler/templates/_result_many.py
baconql/compiler/templates/_result_one.py
baconql/compiler/templates/_result_scalar.py
baconql/compiler/templates/sql.py
baconql/migration/__init__.py
baconql/migration/core.py
baconql/migration/select.py
baconql/migration/utils.py
baconql/migration/version.py
test/__init__.py
test/compiler/__init__.py
test/compiler/conftest.py
test/compiler/test_basic.py
test/compiler/test_basic_loader.py
test/compiler/test_basic_parser.py
test/compiler/test_cli.py
test/compiler/test_typing.py
test/compiler/sql/basic.sql
test/compiler/sql/typing.sql
test/compiler/sql_setup/basic_setup.sql
test/compiler/sql_setup/typing_setup.sql
test/compiler/units/__init__.py
test/compiler/units/test_loader.py
test/compiler/units/test_parser.py
test/migration/__init__.py
test/migration/conftest.py
test/migration/test_m_basic.py
test/migration/test_m_basic_select.py
test/migration/test_m_multiple.py
test/migration/test_m_python.py
test/migration/test_m_python_select.py
test/migration/utils.py
test/migration/m_basic/migration_01.down.sql
test/migration/m_basic/migration_01.up.sql
test/migration/m_basic/migration_02.down.sql
test/migration/m_basic/migration_02.up.sql
test/migration/m_multiple/01_create_one_and_two.down.sql
test/migration/m_multiple/01_create_one_and_two.up.sql
test/migration/m_python/migration_01.down.sql
test/migration/m_python/migration_01.up.sql
test/migration/m_python/migration_02.down.sql
test/migration/m_python/migration_02.up.sql
test/migration/unit/__init__.py
test/migration/unit/test_version.py