Metadata-Version: 1.1
Name: baconql
Version: 0.0.2
Summary: Python SQL without ORM & easy migrations
Home-page: https://github.com/lsenta/baconql
Author: lsenta
Author-email: UNKNOWN
License: UNKNOWN
Platform: UNKNOWN
Classifier: Development Status :: 3 - Alpha
Classifier: Intended Audience :: Developers
Classifier: Programming Language :: Python :: 2
Classifier: Programming Language :: Python :: 2.7
Classifier: Programming Language :: Python :: 3
Classifier: Programming Language :: Python :: 3.5
